my_library/__init__.py
my_library/core.py
my_library/utils.py
openembed/__init__.py
openembed/client.py
openembed/cache/__init__.py
openembed/cache/base.py
openembed/cache/disk.py
openembed/cache/memory.py
openembed/processors/__init__.py
openembed/processors/base.py
openembed/processors/text.py
openembed/providers/__init__.py
openembed/providers/amazon.py
openembed/providers/base.py
openembed/providers/cohere.py
openembed/providers/huggingface.py
openembed/providers/openai.py
openembed/providers/voyageai.py
openembed/utils/__init__.py
openembed/utils/config.py
openembed/utils/errors.py
openembed-0.1.0.dist-info/licenses/LICENSE
openembed-0.1.0.dist-info/METADATA
openembed-0.1.0.dist-info/WHEEL
openembed-0.1.0.dist-info/top_level.txt
openembed-0.1.0.dist-info/RECORD
