Metadata-Version: 2.4
Name: openembed
Version: 0.1.0
Summary: A unified interface for vector embeddings from different providers
Author: OpenEmbed Team
Author-email: OpenEmbed Team <info@openembed.example.com>
License: MIT
Project-URL: Bug Tracker, https://github.com/username/openembed/issues
Project-URL: Documentation, https://openembed.readthedocs.io/
Project-URL: Source Code, https://github.com/username/openembed
Keywords: embeddings,vectors,nlp,ai,machine learning
Classifier: Development Status :: 3 - Alpha
Classifier: Intended Audience :: Developers
Classifier: License :: OSI Approved :: MIT License
Classifier: Programming Language :: Python :: 3
Classifier: Programming Language :: Python :: 3.8
Classifier: Programming Language :: Python :: 3.9
Classifier: Programming Language :: Python :: 3.10
Classifier: Programming Language :: Python :: 3.11
Classifier: Topic :: Scientific/Engineering :: Artificial Intelligence
Classifier: Topic :: Software Development :: Libraries :: Python Modules
Requires-Python: >=3.8
License-File: LICENSE
Requires-Dist: numpy
Requires-Dist: requests
Provides-Extra: openai
Requires-Dist: openai>=1.0.0; extra == "openai"
Provides-Extra: cohere
Requires-Dist: cohere; extra == "cohere"
Provides-Extra: huggingface
Requires-Dist: transformers; extra == "huggingface"
Requires-Dist: torch; extra == "huggingface"
Provides-Extra: voyageai
Requires-Dist: voyageai; extra == "voyageai"
Provides-Extra: amazon
Requires-Dist: boto3; extra == "amazon"
Provides-Extra: all
Requires-Dist: openai>=1.0.0; extra == "all"
Requires-Dist: cohere; extra == "all"
Requires-Dist: transformers; extra == "all"
Requires-Dist: torch; extra == "all"
Requires-Dist: voyageai; extra == "all"
Requires-Dist: boto3; extra == "all"
Provides-Extra: dev
Requires-Dist: pytest; extra == "dev"
Requires-Dist: pytest-cov; extra == "dev"
Requires-Dist: black; extra == "dev"
Requires-Dist: isort; extra == "dev"
Requires-Dist: flake8; extra == "dev"
Requires-Dist: mypy; extra == "dev"
Requires-Dist: sphinx; extra == "dev"
Requires-Dist: sphinx_rtd_theme; extra == "dev"
Dynamic: license-file
Dynamic: requires-python
